testing/__init__.py
testing/test.py
release_testing_ninniet5670-0.1.1.dist-info/METADATA
release_testing_ninniet5670-0.1.1.dist-info/WHEEL
release_testing_ninniet5670-0.1.1.dist-info/entry_points.txt
release_testing_ninniet5670-0.1.1.dist-info/licenses/LICENSE.txt
release_testing_ninniet5670-0.1.1.dist-info/RECORD
