Metadata-Version: 2.1
Name: release-testing-Ninniet5670
Version: 0.1.1
Summary: TESTING NEW PYPROJECT.TOML AND CI/CD
Project-URL: Homepage, https://github.com/Ninniet5670/release-testing
Project-URL: Repository, https://github.com/Ninniet5670/release-testing
Author-email: Marco Aurélio <contato.marcoproenca@gmail.com>
License: Copyright 2023 Marco Aurélio
License-File: LICENSE.txt
Keywords: testing
Classifier: Programming Language :: Python
Requires-Python: >=3.8
Requires-Dist: requests
